geolocation_twitter_scraper/__init__.py
geolocation_twitter_scraper/twitter_scraper.py
geolocation_twitter_scraper-0.0.8.dist-info/LICENSE
geolocation_twitter_scraper-0.0.8.dist-info/METADATA
geolocation_twitter_scraper-0.0.8.dist-info/WHEEL
geolocation_twitter_scraper-0.0.8.dist-info/top_level.txt
geolocation_twitter_scraper-0.0.8.dist-info/RECORD
